{
    "name": "Zambia--0.002--rep3--FS",
    "location": "HPC",
    "suites": [
        {
            "id": "450e832e-f420-e911-a2be-c4346bcb1554",
            "type": "HPC"
        }
    ],
    "iteration": 1,
    "param_names": [
        "SeedYr HIGH",
        "Base Infectivity",
        "Circumcision Reduced Acquire",
        "Sexual Debut Age Female Weibull Scale",
        "Sexual Debut Age Female Weibull Heterogeneity",
        "Sexual Debut Age Male Weibull Scale",
        "Sexual Debut Age Male Weibull Heterogeneity",
        "Trns Form Rate",
        "Infmrl Form Rate",
        "Mrtl Form Rate",
        "Male To Female Young",
        "Male To Female Old",
        "Trns Condom Mid",
        "Trns Condom Rate",
        "Trns Condom Late",
        "Infrml Condom Mid",
        "Infrml Condom Rate",
        "Infmrl Condoms Late",
        "Mrtl Condom Mid",
        "Mrtl Condom Rate",
        "Mrtl Condom Max",
        "Risk Assortivity",
        "Pr Ex Trns Male LOW",
        "Pr Ex Trns Male MED",
        "Pr Ex Trns Fem LOW",
        "Pr Ex Trns Fem MED",
        "Pr Ex Infmrl Male LOW",
        "Pr Ex Infmrl Fem LOW",
        "Max Trns M LOW",
        "Max Trns F LOW",
        "Max Infmrl M LOW",
        "Max Infmrl F LOW",
        "Pr Ex Infmrl Male MED",
        "Pr Ex Infmrl Fem MED",
        "Max Trns M MED",
        "Max Trns F MED",
        "Max Infmrl M MED",
        "Max Infmrl F MED",
        "Max Mrtl M ME",
        "Max Mrtl F ME",
        "Infrml Dur Het",
        "Central: Trns Condoms Late",
        "Central: Infmrl Condoms Late",
        "Central: LOW Risk",
        "Copperbelt: Trns Condoms Late",
        "Copperbelt: Infmrl Condoms Late",
        "Copperbelt: LOW Risk",
        "Eastern: Trns Condoms Late",
        "Eastern: Infmrl Condoms Late",
        "Eastern: LOW Risk",
        "Luapula: Trns Condoms Late",
        "Luapula: Infmrl Condoms Late",
        "Luapula: LOW Risk",
        "Lusaka: Trns Condoms Late",
        "Lusaka: Infmrl Condoms Late",
        "Lusaka: LOW Risk",
        "Muchinga: Trns Condoms Late",
        "Muchinga: Infmrl Condoms Late",
        "Muchinga: LOW Risk",
        "Northern: Trns Condoms Late",
        "Northern: Infmrl Condoms Late",
        "Northern: LOW Risk",
        "Northwestern: Trns Condoms Late",
        "Northwestern: Infmrl Condoms Late",
        "Northwestern: LOW Risk",
        "Southern: Trns Condoms Late",
        "Southern: Infmrl Condoms Late",
        "Southern: LOW Risk",
        "Western: Trns Condoms Late",
        "Western: Infmrl Condoms Late",
        "Western: LOW Risk",
        "PreART Link Min",
        "PreART Link Max",
        "PreART Link Mid",
        "ART Link Max",
        "ART Link Mid",
        "Run_Number"
    ],
    "sites": {
        "Zambia": [
            "HIVCalibSite_Population_Provincial_all_GaussianDistribution",
            "HIVCalibSite_Prevalence_Provincial_all_BetaDistribution",
            "HIVCalibSite_OnART_Provincial_all_GaussianDistribution"
        ]
    },
    "results": {
        "sample": [
            9,
            2,
            4,
            6,
            3,
            5,
            1,
            0,
            8,
            4,
            5,
            9,
            2,
            6,
            8,
            7,
            3,
            1,
            0,
            7
        ],
        "HIVCalibSite_Population_Provincial_all_GaussianDistribution": [
            23.267743591242095,
            22.99630215583364,
            22.19411735485298,
            23.36797011925891,
            22.311173777781566,
            22.335123145355933,
            22.938966052282073,
            22.938966052282073,
            21.852390157533097,
            21.551630007542713,
            22.53040144103738,
            22.57286554934912,
            22.64307240132244,
            22.465097642328775,
            23.022690234817365,
            21.544473906191932,
            21.762643644069488,
            21.805983749990972,
            21.805983749990972,
            22.464942765653984
        ],
        "HIVCalibSite_Prevalence_Provincial_all_BetaDistribution": [
            -69.32061129422998,
            -69.30290417589829,
            -69.2879920575643,
            -69.31222792881691,
            -69.31427813164444,
            -69.31791684106386,
            -69.28932696965235,
            -69.28932696965235,
            -69.31598627925416,
            -69.28955896030583,
            -69.28526285018135,
            -69.31254888915987,
            -69.31347069784856,
            -69.28593644464691,
            -69.28523465594833,
            -69.3215917265976,
            -69.32514210492714,
            -70.83964000000002,
            -70.83964000000002,
            -70.83964000000002
        ],
        "HIVCalibSite_OnART_Provincial_all_GaussianDistribution": [
            8.331157363426728,
            7.749159992585489,
            8.066429081475931,
            6.819880207423089,
            7.48079427844619,
            7.32288670071152,
            6.636643479252415,
            6.636643479252415,
            7.487211498597123,
            7.435765492877241,
            6.438326675733089,
            5.439626300038744,
            5.341728048418779,
            5.3748848973992445,
            4.757829344686544,
            6.252702140744454,
            5.844035889369742,
            5.403440175588681,
            5.403440175588681,
            3.9599605806314373
        ],
        "total": [
            -37.721710339561156,
            -38.55744202747916,
            -39.02744562123539,
            -39.124377602134906,
            -39.52231007541669,
            -39.659906994996405,
            -39.71371743811787,
            -39.71371743811787,
            -39.97638462312395,
            -40.302163459885875,
            -40.31653473341088,
            -41.30005703977201,
            -41.328670248107336,
            -41.445953904918895,
            -41.50471507644443,
            -41.52441567966122,
            -41.71846257148791,
            -43.63021607442036,
            -43.63021607442036,
            -44.41473665371459
        ],
        "ART Link Max": [
            0.9001780375946025,
            0.8974559185625777,
            0.8916195491106724,
            0.8978019775721987,
            0.8842070285137594,
            0.8868829729990425,
            0.891839766984,
            0.891839766984,
            0.9022017462026779,
            0.8982853020090759,
            0.9011154638565914,
            0.8985741876336056,
            0.87723486359667,
            0.8829980585091891,
            0.8781021106316838,
            0.9111439806760236,
            0.8931416056450387,
            0.8921992757301551,
            0.8921992757301551,
            0.8828183873554252
        ],
        "ART Link Mid": [
            1997.6539696692423,
            1996.7839473908562,
            1997.0329945652934,
            1997.1748824504011,
            1997.329525798103,
            1997.21208723833,
            1997.8751006279995,
            1997.8751006279995,
            1997.3192810731784,
            1998.0710570761394,
            1997.818955523446,
            1997.025139104249,
            1997.8863556466374,
            1997.9540551327254,
            1997.8291210007899,
            1997.0802400941404,
            1997.6718040630074,
            1997.1504470324487,
            1997.1504470324487,
            1998.0334529384645
        ],
        "Base Infectivity": [
            0.000666924703915117,
            0.0006537033894825606,
            0.0006513013257715001,
            0.0006559672724573085,
            0.0006556352182859426,
            0.000649596577291786,
            0.00065805,
            0.00065805,
            0.0006433413349991659,
            0.0006541679662681566,
            0.0006761282460393844,
            0.0006632846907915685,
            0.0006527471547529843,
            0.0006643414710609041,
            0.000645713019960304,
            0.0006620168220999619,
            0.0006603752623355827,
            0.0006580500000072615,
            0.0006580500000072615,
            0.0006586529917151143
        ],
        "Central: Infmrl Condoms Late": [
            0.5067300449854417,
            0.5172436468921385,
            0.5159807022884481,
            0.5125532268433957,
            0.5136220600137452,
            0.5159301810179385,
            0.5110263261879998,
            0.5110263261879998,
            0.5037163468598418,
            0.5172215540119393,
            0.5110989899752896,
            0.5144164164357093,
            0.514293961035032,
            0.510336639271005,
            0.5030597112944061,
            0.5084231269584107,
            0.5132721035057844,
            0.5109258509146021,
            0.5109258509146021,
            0.5124424649729752
        ],
        "Central: LOW Risk": [
            0.24328785795772037,
            0.24603459019981122,
            0.2524177673857097,
            0.24513156064629252,
            0.2609633447592948,
            0.254068361804997,
            0.2542050461600001,
            0.2542050461600001,
            0.25552684969518025,
            0.2551073434067773,
            0.26232583505280455,
            0.25672525134524216,
            0.24992571381057166,
            0.2548594208282405,
            0.25570238290486175,
            0.25219853859776775,
            0.2578540201349808,
            0.2541843687831107,
            0.2541843687831107,
            0.25063652005537834
        ],
        "Central: Trns Condoms Late": [
            0.6939404172282814,
            0.6759387082701285,
            0.6925402349749663,
            0.6905581469198274,
            0.7016232218761991,
            0.6916029772637545,
            0.6840104651480003,
            0.6840104651480003,
            0.6808828650521286,
            0.6771811805311841,
            0.689683318525504,
            0.6728216439945731,
            0.6759542823493878,
            0.6811590225383022,
            0.6773457715760695,
            0.6784609472194665,
            0.6800072315251324,
            0.6841797301890757,
            0.6841797301890757,
            0.6868702404654569
        ],
        "Circumcision Reduced Acquire": [
            0.6,
            0.6,
            0.6,
            0.6,
            0.6,
            0.6,
            0.6,
            0.6,
            0.6,
            0.6,
            0.6,
            0.6,
            0.6,
            0.6,
            0.6,
            0.6,
            0.6,
            0.6,
            0.6,
            0.6
        ],
        "Copperbelt: Infmrl Condoms Late": [
            0.2345923405549467,
            0.234857556411279,
            0.23073329251109803,
            0.23090196488481635,
            0.22036778957901437,
            0.2258180318733801,
            0.22692407542000004,
            0.22692407542000004,
            0.1936552914725179,
            0.24218198482979944,
            0.21765047769294427,
            0.235505931882735,
            0.22353706530088968,
            0.22267282311902345,
            0.2311833256588663,
            0.2363279108722601,
            0.2173980251745832,
            0.2274637568308729,
            0.2274637568308729,
            0.22061051975917886
        ],
        "Copperbelt: LOW Risk": [
            0.334309644184816,
            0.33656187323245473,
            0.33476065983704884,
            0.3263702428933525,
            0.33979826291493387,
            0.3304167726255334,
            0.33404160518,
            0.33404160518,
            0.3410279468636591,
            0.3332480219147639,
            0.3365079694163947,
            0.32849062939285945,
            0.3414070735400924,
            0.33275173817060616,
            0.3300501929512772,
            0.3343558769005391,
            0.3340112250041037,
            0.3339836491140134,
            0.3339836491140134,
            0.32230624194711543
        ],
        "Copperbelt: Trns Condoms Late": [
            0.42025042195894236,
            0.42053536322811197,
            0.42509754930757165,
            0.4135340105005181,
            0.4165985954691299,
            0.4235600778886698,
            0.4258758488840002,
            0.4258758488840002,
            0.4169288202935115,
            0.43117657050364877,
            0.44365597025788217,
            0.4295487021495539,
            0.4261349847892411,
            0.4252591176044029,
            0.42131819935014897,
            0.42466751145383413,
            0.4163934810014267,
            0.42556082312180227,
            0.42556082312180227,
            0.42638739505724216
        ],
        "Eastern: Infmrl Condoms Late": [
            0.1647477123794039,
            0.1601704458048636,
            0.17185073123759317,
            0.16625079694759143,
            0.17648930294704912,
            0.1700181998833656,
            0.1703518085240001,
            0.1703518085240001,
            0.17812491856691434,
            0.18003388058292563,
            0.17060295632173073,
            0.1769888370000952,
            0.16690129877799117,
            0.172753077422243,
            0.15823108795869115,
            0.1797922371317162,
            0.18808336102324644,
            0.17022366344202372,
            0.17022366344202372,
            0.1803780203904062
        ],
        "Eastern: LOW Risk": [
            0.12446786113994593,
            0.12596103080594445,
            0.12172400290321203,
            0.12129395714649516,
            0.1251349926733012,
            0.1287638994863798,
            0.12594297065199994,
            0.12594297065199994,
            0.13527868182968802,
            0.12606284959090458,
            0.11837088091975012,
            0.12143887009961665,
            0.1277707598051274,
            0.12339347101105183,
            0.12263407006139089,
            0.1297441438677495,
            0.12130817087936861,
            0.12594175794248497,
            0.12594175794248497,
            0.12284017791130153
        ],
        "Eastern: Trns Condoms Late": [
            0.4887058926684646,
            0.49347309132494027,
            0.507278387047364,
            0.5187084304891654,
            0.5073139186726707,
            0.5093807239878572,
            0.5086235459000004,
            0.5086235459000004,
            0.48320998886675476,
            0.5016633152298826,
            0.5152726852077596,
            0.510910094841835,
            0.5078489217602363,
            0.5094713302094317,
            0.5056593386598315,
            0.5244846644234302,
            0.5124176665472534,
            0.5075333568077693,
            0.5075333568077693,
            0.5188472964410987
        ],
        "Infmrl Condoms Late": [
            0.4483377984228191,
            0.4555084244135669,
            0.4577930340775167,
            0.437958952317116,
            0.45022254962366276,
            0.441818090001688,
            0.4429398756999997,
            0.4429398756999997,
            0.43449095930206444,
            0.4554251855848607,
            0.4469910607063152,
            0.4455088764753925,
            0.4527448821504785,
            0.4422604234185654,
            0.4273478195405345,
            0.44067645044541764,
            0.4353818707105812,
            0.4425568467255191,
            0.4425568467255191,
            0.44301180583915556
        ],
        "Infmrl Form Rate": [
            0.00030469581110412344,
            0.0003447404917885154,
            0.0003452714723399371,
            0.00028196579498011864,
            0.0003176806193367417,
            0.0002951743781470915,
            0.0003267078840000002,
            0.0003267078840000002,
            0.0003529070798777663,
            0.0003088033891111071,
            0.0003314676386556564,
            0.00032807277625282303,
            0.0003297192189119414,
            0.0003295985220011285,
            0.00031136953422370936,
            0.00032811907593726373,
            0.0003409727864249494,
            0.00032670788209256845,
            0.00032670788209256845,
            0.00032807920493758014
        ],
        "Infrml Condom Mid": [
            1996.5320407052484,
            1997.0715708493988,
            1997.7584861833834,
            1998.0052475588016,
            1998.2360863723577,
            1997.527092738295,
            1996.6712737560013,
            1996.6712737560013,
            1997.8328364710078,
            1996.8437555880216,
            1996.9762494719203,
            1997.5973511827233,
            1996.6095267089484,
            1996.4890515086174,
            1996.593281152222,
            1997.5622525533624,
            1996.3861534318155,
            1997.8250592256002,
            1997.8250592256002,
            1996.0953844519886
        ],
        "Infrml Condom Rate": [
            0.35875352177769665,
            0.2538109890411104,
            0.3833069232029428,
            0.34083872276758964,
            0.26648542912750695,
            0.3308197328843487,
            0.32514846760800026,
            0.32514846760800026,
            0.33511737062013924,
            0.32255271157411314,
            0.29053760345713153,
            0.3705742628075839,
            0.3686253287043315,
            0.33352498546638587,
            0.3543002039304737,
            0.3526934122625191,
            0.3012193350821454,
            0.3331124358165667,
            0.3331124358165667,
            0.22186570402656217
        ],
        "Infrml Dur Het": [
            0.75,
            0.75,
            0.75,
            0.75,
            0.75,
            0.75,
            0.75,
            0.75,
            0.75,
            0.75,
            0.75,
            0.75,
            0.75,
            0.75,
            0.75,
            0.75,
            0.75,
            0.75,
            0.75,
            0.75
        ],
        "Luapula: Infmrl Condoms Late": [
            0.5319380760643807,
            0.5342714137861857,
            0.5396851844080603,
            0.5355329616443528,
            0.5385539753603928,
            0.5312825727022654,
            0.5328265342159998,
            0.5328265342159998,
            0.5358846278612799,
            0.5355735206386141,
            0.530905233731333,
            0.5349352467940879,
            0.5329321496862336,
            0.5322623908981933,
            0.5234616391481406,
            0.531698794407694,
            0.5332563723628531,
            0.5328183009140335,
            0.5328183009140335,
            0.5283869244663248
        ],
        "Luapula: LOW Risk": [
            0.23392645924237748,
            0.22786205021192887,
            0.23493379708632992,
            0.22559506067211937,
            0.22557933981933687,
            0.22461170349139342,
            0.23366463305199994,
            0.23366463305199994,
            0.2184892334236456,
            0.2427682536750106,
            0.23592483095314493,
            0.22439074485154217,
            0.24086267440901493,
            0.24803593236368682,
            0.22342483376973288,
            0.226793144367421,
            0.20613889218345097,
            0.23337215625943722,
            0.23337215625943722,
            0.23827703036914466
        ],
        "Luapula: Trns Condoms Late": [
            0.6609927976106009,
            0.6809306338576733,
            0.6660861585418136,
            0.6711307548306275,
            0.6598046877093358,
            0.6610849407296316,
            0.6756244423679993,
            0.6756244423679993,
            0.6781939231414027,
            0.6697469464461542,
            0.65247333892018,
            0.6807418390569239,
            0.6922498322216823,
            0.6822701829655272,
            0.6505391826328015,
            0.659431824413424,
            0.6796566907736049,
            0.6743760091513359,
            0.6743760091513359,
            0.6799857019974709
        ],
        "Lusaka: Infmrl Condoms Late": [
            0.5291302299297821,
            0.5366826235723346,
            0.5378778016487052,
            0.5390005808982322,
            0.5339312633465225,
            0.5407294591103825,
            0.5311928377199998,
            0.5311928377199998,
            0.5352818944071223,
            0.5322197380699404,
            0.526469444724345,
            0.5329933271612962,
            0.5327672011513769,
            0.5300109668330013,
            0.5307120368222908,
            0.5289590962411169,
            0.5310019122295225,
            0.5311769694240748,
            0.5311769694240748,
            0.5320858087076792
        ],
        "Lusaka: LOW Risk": [
            0.3723749980084036,
            0.37608033290360054,
            0.383885361100172,
            0.36882925088653373,
            0.3805870315178288,
            0.3872836627464859,
            0.3806859140840002,
            0.3806859140840002,
            0.3700401373789642,
            0.3754981030477547,
            0.39082304820163605,
            0.38938357300062076,
            0.3805439921224987,
            0.3959953249441485,
            0.38999383068314464,
            0.3803951967322508,
            0.3793836771535108,
            0.3806167298911705,
            0.3806167298911705,
            0.38521405432059275
        ],
        "Lusaka: Trns Condoms Late": [
            0.16336494657226597,
            0.20668005147319715,
            0.1647571993255299,
            0.16927884458271955,
            0.15898676613061716,
            0.16489724266375777,
            0.18005020621200005,
            0.18005020621200005,
            0.2038178187066663,
            0.20266498620474105,
            0.18845964122213443,
            0.16545216525694345,
            0.1977351949014929,
            0.18965729911676082,
            0.16930416873749887,
            0.16250671778368922,
            0.17832415521093462,
            0.17644587331507391,
            0.17644587331507391,
            0.19434832161844198
        ],
        "Male To Female Old": [
            1.772309830892653,
            1.7061644300657224,
            1.7799358980697366,
            1.6404274551353635,
            1.7499337134215833,
            1.6539687684673847,
            1.80702788,
            1.80702788,
            1.7899593159883709,
            1.7811398614259133,
            1.8210597044969243,
            1.8090842821951079,
            1.800812508217906,
            1.762220893656982,
            1.7569493155860707,
            1.8533060257076197,
            1.8300898804061756,
            1.75335329232661,
            1.75335329232661,
            1.8947430997319028
        ],
        "Male To Female Young": [
            2.0921943306629722,
            2.0855542963894913,
            1.9784567440069842,
            2.0488893574304052,
            2.1267723716393228,
            2.098830220712989,
            2.0271207387359995,
            2.0271207387359995,
            2.140527260311022,
            2.0308374954548216,
            1.9950443480575741,
            2.1353903778478576,
            2.0264182981739762,
            2.0743765677962336,
            1.9876323798267883,
            2.0007165468375163,
            2.10132560208999,
            2.085423618468509,
            2.085423618468509,
            2.0245497937849444
        ],
        "Max Infmrl F LOW": [
            1.22953691492827,
            1.1936859514499507,
            1.2202799395244732,
            1.2265070180109319,
            1.2171768076988416,
            1.239440474376343,
            1.220070328784,
            1.220070328784,
            1.2291025491884808,
            1.2304756821023615,
            1.2119868586218008,
            1.2115371279383935,
            1.2327996759437918,
            1.2193887631588274,
            1.2137795883972873,
            1.2127555642226613,
            1.2199089267568335,
            1.2191347811184337,
            1.2191347811184337,
            1.234861436706417
        ],
        "Max Infmrl F MED": [
            2.681274182749806,
            2.7259791745273194,
            2.72038372925725,
            2.726226937119718,
            2.6961492173209267,
            2.726064749083049,
            2.7086229532600004,
            2.7086229532600004,
            2.723175845950445,
            2.6747555057232817,
            2.6912009443173353,
            2.725765004940686,
            2.7176820379234012,
            2.771440946787473,
            2.707154480843072,
            2.7341246635623517,
            2.6855592718402947,
            2.7081995580925144,
            2.7081995580925144,
            2.698049540493937
        ],
        "Max Infmrl M LOW": [
            1.2564008338210253,
            1.2012147403748212,
            1.2285325687880633,
            1.2138491763125356,
            1.2048429543790948,
            1.2405896694804883,
            1.220070328784,
            1.220070328784,
            1.2129180293982547,
            1.2228798044967002,
            1.2134510766173294,
            1.2185950263700558,
            1.2206134805871867,
            1.1964202520322451,
            1.2043136474163731,
            1.2280105484685186,
            1.213602248038545,
            1.220622972405877,
            1.220622972405877,
            1.2256136331596694
        ],
        "Max Infmrl M MED": [
            2.7230811348069297,
            2.7250750963302846,
            2.7171778923103735,
            2.689805086998755,
            2.720848825890407,
            2.732635647572064,
            2.7086229532600004,
            2.7086229532600004,
            2.718139983385678,
            2.710543059454012,
            2.682805866821437,
            2.6807175934852787,
            2.7056204815341407,
            2.7384118100469554,
            2.7416220589488396,
            2.7171350264146703,
            2.716540833530742,
            2.7172789674359312,
            2.7172789674359312,
            2.7080465580819633
        ],
        "Max Mrtl F ME": [
            1.831221961853255,
            1.84339025351576,
            1.8224498937332922,
            1.8441266976708615,
            1.827251084192095,
            1.8257501849091373,
            1.8276888435080003,
            1.8276888435080003,
            1.8139658427169998,
            1.8311417499841456,
            1.841033340418627,
            1.8174648598707006,
            1.8000808730092135,
            1.8256995764684614,
            1.8205020153122438,
            1.8288067330225806,
            1.8410708706226153,
            1.8292922840041395,
            1.8292922840041395,
            1.8343193328637266
        ],
        "Max Mrtl M ME": [
            1.823426557756523,
            1.8366059038061828,
            1.828173706680374,
            1.8328731491019041,
            1.8411357010384666,
            1.8464555735622894,
            1.8276888435080003,
            1.8276888435080003,
            1.8353589231773566,
            1.8067298137160839,
            1.8135912522952102,
            1.8338260453082724,
            1.8167793752859895,
            1.829879026395109,
            1.8132248131513902,
            1.8356962625374948,
            1.8256206954668044,
            1.8280566634282662,
            1.8280566634282662,
            1.8555585889629445
        ],
        "Max Trns F LOW": [
            1.8161148041466537,
            1.8386168842847856,
            1.828235452170747,
            1.826992895604732,
            1.840913334828432,
            1.8359738200443194,
            1.8332489289200007,
            1.8332489289200007,
            1.8369868117718982,
            1.8199575130147554,
            1.821811112818712,
            1.85029466493053,
            1.8306607274820765,
            1.8303238763211545,
            1.83451330181702,
            1.8451418948257314,
            1.8430171486213955,
            1.8333507883266558,
            1.8333507883266558,
            1.8275372525264537
        ],
        "Max Trns F MED": [
            2.2190638948736336,
            2.247534212712414,
            2.1751292161032034,
            2.188910562642933,
            2.288719642478803,
            2.197289094191664,
            2.2127818964040005,
            2.2127818964040005,
            2.214571344603653,
            2.2372907525891885,
            2.238914467267682,
            2.1932030287343056,
            2.2543180392485453,
            2.1919540826855197,
            2.2381986883508405,
            2.2130524063484907,
            2.225486376482328,
            2.187620860900809,
            2.187620860900809,
            2.210020154558852
        ],
        "Max Trns M LOW": [
            1.8381521509390795,
            1.8454399000881816,
            1.8439313331533451,
            1.8207272928486062,
            1.8329576149750542,
            1.8338720826510382,
            1.8332489289200007,
            1.8332489289200007,
            1.8375624867302818,
            1.8445801530725163,
            1.8207667148598732,
            1.8332798980708485,
            1.8730847922539091,
            1.8418233971366844,
            1.8247661595652738,
            1.8368619826310641,
            1.8428527774000663,
            1.8305436189947906,
            1.8305436189947906,
            1.8216217415723093
        ],
        "Max Trns M MED": [
            2.1700817815071924,
            2.157206114848484,
            2.2081107307313457,
            2.129539065492097,
            2.1738830729276417,
            2.1178479050689454,
            2.2127818964040005,
            2.2127818964040005,
            2.224242298130633,
            2.2251769224635902,
            2.205711174306597,
            2.160719314785521,
            2.2129537610071117,
            2.1701912077232333,
            2.2323577219502355,
            2.2371588181855144,
            2.1310196794225935,
            2.2117781875939424,
            2.2117781875939424,
            2.157801737137825
        ],
        "Mrtl Condom Max": [
            0.2452177485624683,
            0.2486872471366162,
            0.2436068637505579,
            0.2349106345256468,
            0.245648019578349,
            0.24809069006690598,
            0.24546589979999997,
            0.24546589979999997,
            0.24096174640008303,
            0.24113728932582873,
            0.25008206594038385,
            0.24361182466922135,
            0.24690656048118437,
            0.24765886388534739,
            0.2443560867549063,
            0.2510729747801135,
            0.24719664070614883,
            0.24544707714034827,
            0.24544707714034827,
            0.2437077708263136
        ],
        "Mrtl Condom Mid": [
            1999.3555615943794,
            2000.2900072483073,
            2000.4731858401667,
            2000.275014923466,
            2000.8377359722526,
            2000.3387832608778,
            1999.4340093160001,
            1999.4340093160001,
            2000.4574860328396,
            1999.3846168314155,
            1999.0625593086925,
            2000.898701012689,
            1999.491436745217,
            1999.580030773635,
            1999.2629863985799,
            2000.8500176107711,
            1999.1795365724613,
            2000.356965053148,
            2000.356965053148,
            1999.5411628326854
        ],
        "Mrtl Condom Rate": [
            1.1893418363082098,
            1.1812056942833464,
            1.0936916682011761,
            1.1250972152290752,
            1.1120398312405668,
            1.1720634871723863,
            1.162613441492,
            1.162613441492,
            1.0937752206102638,
            1.1649122936350307,
            1.2120795860429958,
            1.2070133392645375,
            1.1869225211911056,
            1.1959595450924252,
            1.1652175740523874,
            1.1256037107714487,
            1.186231686124246,
            1.151995875005513,
            1.151995875005513,
            1.1506023939025132
        ],
        "Mrtl Form Rate": [
            0.00014981506142422443,
            0.00015448795858989,
            0.00015641447756626608,
            0.0001474042266628404,
            0.00015041179521167798,
            0.00014864375143000235,
            0.00015194086800000004,
            0.00015194086800000004,
            0.00015028487134046372,
            0.0001518071894472911,
            0.00014634426556002283,
            0.00014690520074378609,
            0.00014759584366402215,
            0.0001497491652629533,
            0.00014579826416065837,
            0.00015384042484888663,
            0.00014947049426455687,
            0.0001519408680168465,
            0.0001519408680168465,
            0.00015441983263187733
        ],
        "Muchinga: Infmrl Condoms Late": [
            0.21775689505558235,
            0.20516399464330862,
            0.20627201451000696,
            0.1844228007113802,
            0.20824224067553787,
            0.20856937618141183,
            0.20668921986799996,
            0.20668921986799996,
            0.19948300351949952,
            0.2077279796023681,
            0.2051656234595515,
            0.19179376260727216,
            0.22003025440956397,
            0.21553747310809754,
            0.2053972779918758,
            0.20045601505745192,
            0.20761150750906168,
            0.20615445597271062,
            0.20615445597271062,
            0.20209178946335724
        ],
        "Muchinga: LOW Risk": [
            0.09420522115736712,
            0.1017868139923503,
            0.09737936473331502,
            0.09563049490263378,
            0.09348552845157243,
            0.09150996016242553,
            0.09272307417600002,
            0.09272307417600002,
            0.08540504825158504,
            0.09182752750301829,
            0.0950460905166002,
            0.0953768303779668,
            0.09681750306255295,
            0.09417197136217753,
            0.09517390226258908,
            0.0874626480518168,
            0.09444446908879582,
            0.09268500580114868,
            0.09268500580114868,
            0.09503257818949355
        ],
        "Muchinga: Trns Condoms Late": [
            0.4880374150928498,
            0.468028885273971,
            0.4836951751313833,
            0.4920628609452423,
            0.479620415660942,
            0.4980586761554767,
            0.48440360224799983,
            0.48440360224799983,
            0.4859995310257681,
            0.49054116355265776,
            0.4669088668044319,
            0.5019230678928885,
            0.48765066741224056,
            0.5001446359172635,
            0.48348848395931676,
            0.4994915137378246,
            0.5007177665389976,
            0.4846325342464714,
            0.4846325342464714,
            0.4953695275409913
        ],
        "Northern: Infmrl Condoms Late": [
            0.4914384944148777,
            0.5073454592690374,
            0.49278102552691355,
            0.48100167523413884,
            0.5029531087346946,
            0.4758140130361423,
            0.4876322350719995,
            0.4876322350719995,
            0.4674232891899302,
            0.5012688798896775,
            0.48661873110483606,
            0.49232791315911456,
            0.48678140623128485,
            0.4885712763703855,
            0.5036463562749043,
            0.4988530065661984,
            0.5105073760699538,
            0.487970646449053,
            0.487970646449053,
            0.4894024659455978
        ],
        "Northern: LOW Risk": [
            0.4484971525087149,
            0.4459335433362872,
            0.44987987166311744,
            0.4530058314993854,
            0.45603605655138013,
            0.4552655948772395,
            0.44898045094000005,
            0.44898045094000005,
            0.44535605637957926,
            0.447922808321504,
            0.45243628429145333,
            0.44388212658119175,
            0.44487872492571146,
            0.44512286426234343,
            0.44744539165384895,
            0.4486786482094402,
            0.4579271553751989,
            0.4489901993867876,
            0.4489901993867876,
            0.4496016439724602
        ],
        "Northern: Trns Condoms Late": [
            0.6120360623537519,
            0.6082050467633402,
            0.6067236023222975,
            0.5944951494071573,
            0.6038311821708484,
            0.6181406907911283,
            0.6079084890999997,
            0.6079084890999997,
            0.609228804154271,
            0.5962146034056159,
            0.6129173636396396,
            0.5967175058727485,
            0.6152445419110769,
            0.6000371468646462,
            0.6177928028229729,
            0.6125269640166637,
            0.6221403888890522,
            0.6075029411751104,
            0.6075029411751104,
            0.6101874397346942
        ],
        "Northwestern: Infmrl Condoms Late": [
            0.4945430624164024,
            0.47904558123750296,
            0.47717232347801314,
            0.48714937722746154,
            0.475072680581717,
            0.4826275672504342,
            0.48899453800799997,
            0.48899453800799997,
            0.4919420054965958,
            0.4759788650399114,
            0.4763018785054003,
            0.4831497916192547,
            0.49252200178080313,
            0.49295372786679276,
            0.4791825021228654,
            0.4669016809262789,
            0.4737617634856278,
            0.4889739651770652,
            0.4889739651770652,
            0.49736047330750216
        ],
        "Northwestern: LOW Risk": [
            0.27565926572444027,
            0.2844121523136332,
            0.28703068677700383,
            0.30393940973126315,
            0.2976729197499423,
            0.2940785858292482,
            0.2914405509600002,
            0.2914405509600002,
            0.29706188581131604,
            0.29581633403128194,
            0.27298428158579535,
            0.31075728475598224,
            0.29738787117036347,
            0.30135761225695107,
            0.3022659112360822,
            0.3027948433987588,
            0.31066208637737697,
            0.2911537907273362,
            0.2911537907273362,
            0.3125140490266784
        ],
        "Northwestern: Trns Condoms Late": [
            0.6580872094293743,
            0.6596361880985128,
            0.6545776436256399,
            0.6635719267245556,
            0.6562714847636506,
            0.6444394084642611,
            0.6544284567199999,
            0.6544284567199999,
            0.6530325972062888,
            0.644024398639559,
            0.6597009933070245,
            0.6413773998563876,
            0.656272089058217,
            0.6539936995774867,
            0.6486518696237654,
            0.6522007990115563,
            0.6524958495250739,
            0.654243188182347,
            0.654243188182347,
            0.663860446988847
        ],
        "Pr Ex Infmrl Fem LOW": [
            0.2971389838458209,
            0.305616091569719,
            0.31811746711009015,
            0.30855471522665223,
            0.29767382996045955,
            0.29126223406745316,
            0.3005679004599999,
            0.3005679004599999,
            0.2984947776848564,
            0.3122871862071753,
            0.29871987958919594,
            0.2979265711146552,
            0.29916045386254964,
            0.29915502822938045,
            0.29679363820080623,
            0.30656319961435613,
            0.31150351003009774,
            0.30056573182244495,
            0.30056573182244495,
            0.300354992551712
        ],
        "Pr Ex Infmrl Fem MED": [
            0.397798862923048,
            0.39096261764727563,
            0.3977704564382727,
            0.386299990429898,
            0.38419620198518667,
            0.39062740998699996,
            0.3926795025160002,
            0.3926795025160002,
            0.38647501702549447,
            0.3925678476203804,
            0.3828285623572665,
            0.3885744615540261,
            0.385243812987164,
            0.3987345391030626,
            0.39174686022664756,
            0.3868774842101529,
            0.39384185629195845,
            0.39297478623851134,
            0.39297478623851134,
            0.3956717440399111
        ],
        "Pr Ex Infmrl Male LOW": [
            0.24301243869657327,
            0.27971836551813156,
            0.25784039395062514,
            0.24988771836662066,
            0.26948265131637694,
            0.26762294439178846,
            0.26551587058400006,
            0.26551587058400006,
            0.2518593612529388,
            0.27894101385936654,
            0.26683349267739787,
            0.2801230474456623,
            0.25310631048664617,
            0.25252895447923684,
            0.2408336352031335,
            0.2643348381770887,
            0.26382780564862957,
            0.2654711453435126,
            0.2654711453435126,
            0.2556276598194363
        ],
        "Pr Ex Infmrl Male MED": [
            0.4127675641317762,
            0.4168504446643462,
            0.42396847562931333,
            0.41310829161670426,
            0.40967711496222564,
            0.41046389488625745,
            0.4110081915719999,
            0.4110081915719999,
            0.402846259303255,
            0.413502563798217,
            0.4160289316837447,
            0.41386454926889255,
            0.413650596770145,
            0.39912594676958196,
            0.41302391198219707,
            0.4008105809569454,
            0.42031947088854327,
            0.4109315014909864,
            0.4109315014909864,
            0.4055778243728097
        ],
        "Pr Ex Trns Fem LOW": [
            0.05234498617361072,
            0.052954265479805175,
            0.05868086854768741,
            0.06164564140191957,
            0.06499973317373597,
            0.07151939534701413,
            0.060158364316,
            0.060158364316,
            0.06454384983061782,
            0.058939502983209484,
            0.0552061780933105,
            0.06161738158358773,
            0.0625192033129067,
            0.05599954807257208,
            0.06005216299559924,
            0.05781536006432471,
            0.058349539993057316,
            0.06013899821935255,
            0.06013899821935255,
            0.05403548624600774
        ],
        "Pr Ex Trns Fem MED": [
            0.3430601658766719,
            0.34650337038981954,
            0.32070832881194616,
            0.3167179707241441,
            0.3259178515695975,
            0.32774570008053233,
            0.32757797660000004,
            0.32757797660000004,
            0.32666413204922895,
            0.336189940105949,
            0.30473307204713806,
            0.3333806489977823,
            0.3131154516226965,
            0.3350172241213564,
            0.3246783139798176,
            0.3521442760273648,
            0.3260749575677212,
            0.3301863754840573,
            0.3301863754840573,
            0.3244561501946505
        ],
        "Pr Ex Trns Male LOW": [
            0.17459318075220204,
            0.17120049159436534,
            0.17857135930052237,
            0.17346040649488084,
            0.16325258238163187,
            0.16875202162555647,
            0.17156243564800003,
            0.17156243564800003,
            0.1751310979235072,
            0.17849503103710299,
            0.18004997860952127,
            0.16612748107048958,
            0.1688374702338522,
            0.17723268301327894,
            0.18763972484730687,
            0.1733281023435451,
            0.17360860298219497,
            0.17168553570294018,
            0.17168553570294018,
            0.172020271878072
        ],
        "Pr Ex Trns Male MED": [
            0.31365254315186314,
            0.2930943590890347,
            0.2935993184726117,
            0.28214685138144446,
            0.30592482130750687,
            0.3152197199606915,
            0.2968423946159999,
            0.2968423946159999,
            0.28771334593074055,
            0.2871040374117293,
            0.30778194907992634,
            0.29857606699221423,
            0.3023993303045863,
            0.28175566378308253,
            0.2815636857517406,
            0.3084507297350772,
            0.3036613767023693,
            0.29640140583699126,
            0.29640140583699126,
            0.2892602532196797
        ],
        "PreART Link Max": [
            0.9579446613919206,
            0.9637551357976838,
            0.9602891855611086,
            0.9533597244648231,
            0.966448624063661,
            0.9620253115330429,
            0.9633467164679995,
            0.9633467164679995,
            0.9695325207296164,
            0.9730602629858766,
            0.9594528547772755,
            0.9546865176194073,
            0.9616733472619543,
            0.9655485899029455,
            0.9611025924600267,
            0.9694700934255758,
            0.9568110727418643,
            0.9633395162018358,
            0.9633395162018358,
            0.9707541154029559
        ],
        "PreART Link Mid": [
            2006.6245543991693,
            2006.8770336428167,
            2006.6248243420887,
            2006.6513477069357,
            2006.5683782722108,
            2006.5194414844048,
            2006.542934072,
            2006.542934072,
            2006.422516025194,
            2006.6257570940231,
            2006.4786083700178,
            2006.4288940972112,
            2006.5858066050666,
            2006.7410743591652,
            2006.363061712689,
            2006.1795085902427,
            2006.6416262162254,
            2006.5371941533144,
            2006.5371941533144,
            2006.6869161338602
        ],
        "PreART Link Min": [
            0.8379627574563892,
            0.8306838667108623,
            0.8537263097411798,
            0.8299273324188101,
            0.8503205448820468,
            0.8311231756425128,
            0.8375269584079996,
            0.8375269584079996,
            0.8225263202796826,
            0.8517194647634355,
            0.8496097627236096,
            0.8394583233854854,
            0.8440857883184896,
            0.8335498480735833,
            0.8340632233350687,
            0.8372162793751674,
            0.8287010934762846,
            0.8368985413817556,
            0.8368985413817556,
            0.8465232203369414
        ],
        "Risk Assortivity": [
            0.17196566636811708,
            0.14850763495725447,
            0.16761532375981303,
            0.1610641421336523,
            0.1463141882553539,
            0.16758414073364505,
            0.1583939125279999,
            0.1583939125279999,
            0.14915528399914962,
            0.1556547691839832,
            0.1521829387627638,
            0.16918104523390767,
            0.14217306749447484,
            0.16034701174014102,
            0.15559217687344273,
            0.17866284898678342,
            0.14691696619102126,
            0.15940570477853744,
            0.15940570477853744,
            0.15308575966540663
        ],
        "Run_Number": [
            4607.0,
            6749.671725360457,
            4912.477845936287,
            4607.0,
            5316.568959581973,
            5076.412141895578,
            4931.0,
            4931.0,
            4607.0,
            4827.6311406503,
            4618.083236428867,
            4607.0,
            5216.32469288754,
            6214.451670371266,
            6091.886875594263,
            4824.821443990806,
            6462.47488164656,
            4607.0,
            4607.0,
            5529.8049442816755
        ],
        "SeedYr HIGH": [
            1982.0,
            1982.0,
            1982.0,
            1982.0,
            1982.0,
            1982.0,
            1982.0,
            1982.0,
            1982.0,
            1982.0,
            1982.0,
            1982.0,
            1982.0,
            1982.0,
            1982.0,
            1982.0,
            1982.0,
            1982.0,
            1982.0,
            1982.0
        ],
        "Sexual Debut Age Female Weibull Heterogeneity": [
            0.2166833166629767,
            0.2313758449014218,
            0.21901708210052653,
            0.23377277002209734,
            0.2300415585188675,
            0.2145609987219939,
            0.22594080922800006,
            0.22594080922800006,
            0.2217709671513099,
            0.22612604773695505,
            0.2288814244295072,
            0.22079261867461994,
            0.22545271500490965,
            0.23124415501949394,
            0.2217145542900272,
            0.23296275852403261,
            0.2235215635589345,
            0.22589191718716606,
            0.22589191718716606,
            0.2221986129375273
        ],
        "Sexual Debut Age Female Weibull Scale": [
            18.591382895060185,
            18.577404755479314,
            18.568859514591384,
            18.599430409079975,
            18.64690460232671,
            18.6647051891105,
            18.606144675919992,
            18.606144675919992,
            18.699556533271252,
            18.72300656108979,
            18.58713672284396,
            18.641336456341183,
            18.54276861414029,
            18.48844857285213,
            18.53544693287794,
            18.62049870863116,
            18.610607624501455,
            18.661830907578317,
            18.661830907578317,
            18.622743714399874
        ],
        "Sexual Debut Age Male Weibull Heterogeneity": [
            0.1633417670597011,
            0.16918909269792146,
            0.17654383620340436,
            0.16915286400470705,
            0.17358740016611185,
            0.17635033986036486,
            0.16722784289600007,
            0.16722784289600007,
            0.1647191723870402,
            0.17244215402569574,
            0.1861189178370034,
            0.1698545251047512,
            0.16347585551476498,
            0.1725823900895966,
            0.16823426252458648,
            0.17349459575796294,
            0.17108088097082416,
            0.1671342881528871,
            0.1671342881528871,
            0.17716256470446012
        ],
        "Sexual Debut Age Male Weibull Scale": [
            16.4618015510158,
            16.56338740731446,
            16.739449770102105,
            16.58630692757432,
            16.595740964861907,
            16.631608042205073,
            16.529063348719998,
            16.529063348719998,
            16.5486362287275,
            16.644019750324055,
            16.569311311458247,
            16.73800141686203,
            16.486333374968297,
            16.583789247078055,
            16.52492516890342,
            16.542599725789447,
            16.500681851146563,
            16.574246869940236,
            16.574246869940236,
            16.525636687474584
        ],
        "Southern: Infmrl Condoms Late": [
            0.5280006064902603,
            0.5236902437568373,
            0.5320748670022835,
            0.5278385892176674,
            0.5200573818155182,
            0.5286105913969835,
            0.5269561592559996,
            0.5269561592559996,
            0.5294381925329863,
            0.529130805172258,
            0.5209208772275125,
            0.5210599594543771,
            0.5183890600153027,
            0.5348301307480872,
            0.5130782193548121,
            0.539048668075813,
            0.5156247520786581,
            0.5271138067212577,
            0.5271138067212577,
            0.5292697320093236
        ],
        "Southern: LOW Risk": [
            0.36857202737353684,
            0.3623581874077611,
            0.3745347834659841,
            0.370402103211221,
            0.3819956971835411,
            0.3787936142546387,
            0.3741192799080003,
            0.3741192799080003,
            0.3749380743773118,
            0.37552008011392624,
            0.3753690247315553,
            0.3736202533677613,
            0.3762634976974193,
            0.3771513522613494,
            0.3775528560821528,
            0.37845184319454955,
            0.36978516893939184,
            0.37408332259427707,
            0.37408332259427707,
            0.36947649540558586
        ],
        "Southern: Trns Condoms Late": [
            0.7323192034170066,
            0.7378764354179888,
            0.7335756965072848,
            0.7318770251576645,
            0.72649423180825,
            0.739635636484615,
            0.7308442738000007,
            0.7308442738000007,
            0.7249701757086919,
            0.7201914542967072,
            0.7210218660132641,
            0.7310254133608185,
            0.7285783953692083,
            0.735429572694469,
            0.730188403801951,
            0.7301936440998333,
            0.7301244840953149,
            0.7309548093994096,
            0.7309548093994096,
            0.7413430473175575
        ],
        "Trns Condom Late": [
            0.3016804363672569,
            0.2722168959458601,
            0.3054828597035958,
            0.26744936594545243,
            0.29802585510113455,
            0.2868092973805426,
            0.29476792519999995,
            0.29476792519999995,
            0.30041009886776976,
            0.28421767638644185,
            0.2835329753839316,
            0.2948892752942696,
            0.3069059256426901,
            0.28710688001939194,
            0.2920216061677886,
            0.29540084267427513,
            0.3053802052391533,
            0.29440210778614856,
            0.29440210778614856,
            0.2887884644852153
        ],
        "Trns Condom Mid": [
            2003.721491568644,
            2003.558766746489,
            2003.7128675682532,
            2003.7883321701104,
            2003.5478535203295,
            2003.632995630484,
            2003.6462943840002,
            2003.6462943840002,
            2003.8390801084174,
            2003.629119690963,
            2003.5801858707312,
            2003.529869099317,
            2003.7212382407247,
            2003.6158102739766,
            2003.6183187786378,
            2003.590147023369,
            2003.6759499794082,
            2003.6490198979127,
            2003.6490198979127,
            2003.6218442433742
        ],
        "Trns Condom Rate": [
            2.694612647537379,
            2.623520060109867,
            2.6809839577162577,
            2.676752878831088,
            2.6951346160620653,
            2.636698809221437,
            2.680546492368,
            2.680546492368,
            2.6995950546779053,
            2.6575796498779636,
            2.6712777493193416,
            2.6698585799558705,
            2.6814729224614995,
            2.737621946589737,
            2.6477294153321225,
            2.708657913705503,
            2.646350585177163,
            2.6795319432585725,
            2.6795319432585725,
            2.7316356431329054
        ],
        "Trns Form Rate": [
            0.001333171837660531,
            0.0013118506601456953,
            0.0013732401031578472,
            0.0013587692717586225,
            0.0013847670010412583,
            0.0013578736769404996,
            0.0013502689680000004,
            0.0013502689680000004,
            0.0013366284455413704,
            0.001332741781731753,
            0.001378070107081174,
            0.0014022468320460113,
            0.0013715811773102194,
            0.001351265670396663,
            0.0013310033739603168,
            0.0013754892389425389,
            0.0013348236495621098,
            0.0013502689353498637,
            0.0013502689353498637,
            0.0013676611645764376
        ],
        "Western: Infmrl Condoms Late": [
            0.07766690238960289,
            0.08297359828189899,
            0.08852753156340387,
            0.08463207677435673,
            0.07766205792060883,
            0.0651836779505489,
            0.08501450512400001,
            0.08501450512400001,
            0.08047433684306726,
            0.093547617423934,
            0.08210858462818221,
            0.09382163699691023,
            0.07051435646947546,
            0.08225790476190699,
            0.08032037249934941,
            0.07447030609483848,
            0.08518917518795532,
            0.08542565052202807,
            0.08542565052202807,
            0.0674701634426445
        ],
        "Western: LOW Risk": [
            0.27639171625494713,
            0.26668815607993696,
            0.27018806328477873,
            0.2776517488439093,
            0.2769122610259039,
            0.2684474857628029,
            0.2780668342160001,
            0.2780668342160001,
            0.2730692321242028,
            0.27348937091977965,
            0.284290192489778,
            0.289667888686531,
            0.27910411984564293,
            0.26872928948914276,
            0.2778018620443948,
            0.28772551294542165,
            0.264650965568592,
            0.2780598181678455,
            0.2780598181678455,
            0.25600724639599554
        ],
        "Western: Trns Condoms Late": [
            0.6247558127895362,
            0.6502833466009186,
            0.6291891765902397,
            0.6354988476921851,
            0.6448501150412951,
            0.6315601151081989,
            0.6406304791040001,
            0.6406304791040001,
            0.6380922023201363,
            0.6362328106718678,
            0.6421374365725893,
            0.6417623245140556,
            0.6328878249802993,
            0.6500797211984863,
            0.6279943328176136,
            0.635569047468622,
            0.6336495562797905,
            0.6407113115583469,
            0.6407113115583469,
            0.6334477721983985
        ],
        "iteration": [
            0,
            1,
            1,
            1,
            1,
            1,
            0,
            0,
            1,
            0,
            0,
            1,
            0,
            0,
            0,
            1,
            0,
            1,
            1,
            0
        ]
    },
    "setup_overlay_file": null,
    "selected_block": "HPC",
    "calibration_start": "2019-01-25 14:54:33",
    "final_samples": {
        "SeedYr HIGH": [
            1982.0
        ],
        "Base Infectivity": [
            0.0006580500000072615
        ],
        "Circumcision Reduced Acquire": [
            0.6
        ],
        "Sexual Debut Age Female Weibull Scale": [
            18.661830907578317
        ],
        "Sexual Debut Age Female Weibull Heterogeneity": [
            0.22589191718716606
        ],
        "Sexual Debut Age Male Weibull Scale": [
            16.574246869940236
        ],
        "Sexual Debut Age Male Weibull Heterogeneity": [
            0.1671342881528871
        ],
        "Trns Form Rate": [
            0.0013502689353498637
        ],
        "Infmrl Form Rate": [
            0.00032670788209256845
        ],
        "Mrtl Form Rate": [
            0.0001519408680168465
        ],
        "Male To Female Young": [
            2.085423618468509
        ],
        "Male To Female Old": [
            1.75335329232661
        ],
        "Trns Condom Mid": [
            2003.6490198979127
        ],
        "Trns Condom Rate": [
            2.6795319432585725
        ],
        "Trns Condom Late": [
            0.29440210778614856
        ],
        "Infrml Condom Mid": [
            1997.8250592256002
        ],
        "Infrml Condom Rate": [
            0.3331124358165667
        ],
        "Infmrl Condoms Late": [
            0.4425568467255191
        ],
        "Mrtl Condom Mid": [
            2000.356965053148
        ],
        "Mrtl Condom Rate": [
            1.151995875005513
        ],
        "Mrtl Condom Max": [
            0.24544707714034827
        ],
        "Risk Assortivity": [
            0.15940570477853744
        ],
        "Pr Ex Trns Male LOW": [
            0.17168553570294018
        ],
        "Pr Ex Trns Male MED": [
            0.29640140583699126
        ],
        "Pr Ex Trns Fem LOW": [
            0.06013899821935255
        ],
        "Pr Ex Trns Fem MED": [
            0.3301863754840573
        ],
        "Pr Ex Infmrl Male LOW": [
            0.2654711453435126
        ],
        "Pr Ex Infmrl Fem LOW": [
            0.30056573182244495
        ],
        "Max Trns M LOW": [
            1.8305436189947906
        ],
        "Max Trns F LOW": [
            1.8333507883266558
        ],
        "Max Infmrl M LOW": [
            1.220622972405877
        ],
        "Max Infmrl F LOW": [
            1.2191347811184337
        ],
        "Pr Ex Infmrl Male MED": [
            0.4109315014909864
        ],
        "Pr Ex Infmrl Fem MED": [
            0.39297478623851134
        ],
        "Max Trns M MED": [
            2.2117781875939424
        ],
        "Max Trns F MED": [
            2.187620860900809
        ],
        "Max Infmrl M MED": [
            2.7172789674359312
        ],
        "Max Infmrl F MED": [
            2.7081995580925144
        ],
        "Max Mrtl M ME": [
            1.8280566634282662
        ],
        "Max Mrtl F ME": [
            1.8292922840041395
        ],
        "Infrml Dur Het": [
            0.75
        ],
        "Central: Trns Condoms Late": [
            0.6841797301890757
        ],
        "Central: Infmrl Condoms Late": [
            0.5109258509146021
        ],
        "Central: LOW Risk": [
            0.2541843687831107
        ],
        "Copperbelt: Trns Condoms Late": [
            0.42556082312180227
        ],
        "Copperbelt: Infmrl Condoms Late": [
            0.2274637568308729
        ],
        "Copperbelt: LOW Risk": [
            0.3339836491140134
        ],
        "Eastern: Trns Condoms Late": [
            0.5075333568077693
        ],
        "Eastern: Infmrl Condoms Late": [
            0.17022366344202372
        ],
        "Eastern: LOW Risk": [
            0.12594175794248497
        ],
        "Luapula: Trns Condoms Late": [
            0.6743760091513359
        ],
        "Luapula: Infmrl Condoms Late": [
            0.5328183009140335
        ],
        "Luapula: LOW Risk": [
            0.23337215625943722
        ],
        "Lusaka: Trns Condoms Late": [
            0.17644587331507391
        ],
        "Lusaka: Infmrl Condoms Late": [
            0.5311769694240748
        ],
        "Lusaka: LOW Risk": [
            0.3806167298911705
        ],
        "Muchinga: Trns Condoms Late": [
            0.4846325342464714
        ],
        "Muchinga: Infmrl Condoms Late": [
            0.20615445597271062
        ],
        "Muchinga: LOW Risk": [
            0.09268500580114868
        ],
        "Northern: Trns Condoms Late": [
            0.6075029411751104
        ],
        "Northern: Infmrl Condoms Late": [
            0.487970646449053
        ],
        "Northern: LOW Risk": [
            0.4489901993867876
        ],
        "Northwestern: Trns Condoms Late": [
            0.654243188182347
        ],
        "Northwestern: Infmrl Condoms Late": [
            0.4889739651770652
        ],
        "Northwestern: LOW Risk": [
            0.2911537907273362
        ],
        "Southern: Trns Condoms Late": [
            0.7309548093994096
        ],
        "Southern: Infmrl Condoms Late": [
            0.5271138067212577
        ],
        "Southern: LOW Risk": [
            0.37408332259427707
        ],
        "Western: Trns Condoms Late": [
            0.6407113115583469
        ],
        "Western: Infmrl Condoms Late": [
            0.08542565052202807
        ],
        "Western: LOW Risk": [
            0.2780598181678455
        ],
        "PreART Link Min": [
            0.8368985413817556
        ],
        "PreART Link Max": [
            0.9633395162018358
        ],
        "PreART Link Mid": [
            2006.5371941533144
        ],
        "ART Link Max": [
            0.8921992757301551
        ],
        "ART Link Mid": [
            1997.1504470324487
        ],
        "Run_Number": [
            4607.0
        ]
    },
    "final_samples_dtypes": {
        "SeedYr HIGH": "object",
        "Base Infectivity": "object",
        "Circumcision Reduced Acquire": "object",
        "Sexual Debut Age Female Weibull Scale": "object",
        "Sexual Debut Age Female Weibull Heterogeneity": "object",
        "Sexual Debut Age Male Weibull Scale": "object",
        "Sexual Debut Age Male Weibull Heterogeneity": "object",
        "Trns Form Rate": "object",
        "Infmrl Form Rate": "object",
        "Mrtl Form Rate": "object",
        "Male To Female Young": "object",
        "Male To Female Old": "object",
        "Trns Condom Mid": "object",
        "Trns Condom Rate": "object",
        "Trns Condom Late": "object",
        "Infrml Condom Mid": "object",
        "Infrml Condom Rate": "object",
        "Infmrl Condoms Late": "object",
        "Mrtl Condom Mid": "object",
        "Mrtl Condom Rate": "object",
        "Mrtl Condom Max": "object",
        "Risk Assortivity": "object",
        "Pr Ex Trns Male LOW": "object",
        "Pr Ex Trns Male MED": "object",
        "Pr Ex Trns Fem LOW": "object",
        "Pr Ex Trns Fem MED": "object",
        "Pr Ex Infmrl Male LOW": "object",
        "Pr Ex Infmrl Fem LOW": "object",
        "Max Trns M LOW": "object",
        "Max Trns F LOW": "object",
        "Max Infmrl M LOW": "object",
        "Max Infmrl F LOW": "object",
        "Pr Ex Infmrl Male MED": "object",
        "Pr Ex Infmrl Fem MED": "object",
        "Max Trns M MED": "object",
        "Max Trns F MED": "object",
        "Max Infmrl M MED": "object",
        "Max Infmrl F MED": "object",
        "Max Mrtl M ME": "object",
        "Max Mrtl F ME": "object",
        "Infrml Dur Het": "object",
        "Central: Trns Condoms Late": "object",
        "Central: Infmrl Condoms Late": "object",
        "Central: LOW Risk": "object",
        "Copperbelt: Trns Condoms Late": "object",
        "Copperbelt: Infmrl Condoms Late": "object",
        "Copperbelt: LOW Risk": "object",
        "Eastern: Trns Condoms Late": "object",
        "Eastern: Infmrl Condoms Late": "object",
        "Eastern: LOW Risk": "object",
        "Luapula: Trns Condoms Late": "object",
        "Luapula: Infmrl Condoms Late": "object",
        "Luapula: LOW Risk": "object",
        "Lusaka: Trns Condoms Late": "object",
        "Lusaka: Infmrl Condoms Late": "object",
        "Lusaka: LOW Risk": "object",
        "Muchinga: Trns Condoms Late": "object",
        "Muchinga: Infmrl Condoms Late": "object",
        "Muchinga: LOW Risk": "object",
        "Northern: Trns Condoms Late": "object",
        "Northern: Infmrl Condoms Late": "object",
        "Northern: LOW Risk": "object",
        "Northwestern: Trns Condoms Late": "object",
        "Northwestern: Infmrl Condoms Late": "object",
        "Northwestern: LOW Risk": "object",
        "Southern: Trns Condoms Late": "object",
        "Southern: Infmrl Condoms Late": "object",
        "Southern: LOW Risk": "object",
        "Western: Trns Condoms Late": "object",
        "Western: Infmrl Condoms Late": "object",
        "Western: LOW Risk": "object",
        "PreART Link Min": "object",
        "PreART Link Max": "object",
        "PreART Link Mid": "object",
        "ART Link Max": "object",
        "ART Link Mid": "object",
        "Run_Number": "object"
    }
}